Tic_tac_toe_GBHomework/__init__.py
Tic_tac_toe_GBHomework-1.0.dist-info/METADATA
Tic_tac_toe_GBHomework-1.0.dist-info/WHEEL
Tic_tac_toe_GBHomework-1.0.dist-info/top_level.txt
Tic_tac_toe_GBHomework-1.0.dist-info/RECORD
