Metadata-Version: 2.1
Name: Tic-tac-toe-GBHomework
Version: 1.0
Summary: GB Homework
Author: MrFlansDay
Author-email: lexa2004924@gmail.com
Classifier: Programming Language :: Python :: 3
Classifier: License :: OSI Approved :: MIT License
Classifier: Operating System :: OS Independent
Requires-Python: >=3.6
